smthit/__init__.py
smthit/core/__init__.py
smthit/core/logging/__init__.py
smthit/core/sys/__init__.py
smthit/core/sys/sys_info.py
smthit/core/utils/__init__.py
smthit/core/utils/base64_util.py
smthit/core/utils/logger_util.py
smthit/core/utils/md5_util.py
smthit/core/web/__init__.py
smthit/core/web/common.py
smthit_core-0.1.0.dist-info/METADATA
smthit_core-0.1.0.dist-info/WHEEL
smthit_core-0.1.0.dist-info/top_level.txt
smthit_core-0.1.0.dist-info/RECORD
